pydmnrules_mcp/__init__.py
pydmnrules_mcp/server.py
pydmnrules_mcp_server-1.1.0.dist-info/licenses/LICENSE
pydmnrules_mcp_server-1.1.0.dist-info/licenses/LICENSE_MCP
pydmnrules_mcp_server-1.1.0.dist-info/METADATA
pydmnrules_mcp_server-1.1.0.dist-info/WHEEL
pydmnrules_mcp_server-1.1.0.dist-info/entry_points.txt
pydmnrules_mcp_server-1.1.0.dist-info/top_level.txt
pydmnrules_mcp_server-1.1.0.dist-info/RECORD
