Metadata-Version: 2.4
Name: pydmnrules-mcp-server
Version: 1.1.0
Summary: MCP server for pyDMNrules-enhanced - enables LLMs to execute DMN decision rules with DRD support
Home-page: https://github.com/uengine/pyDMNrules
Author: uengine (rickjang)
Author-email: rick.jang@uengine.org
Project-URL: Documentation, https://github.com/uengine/pyDMNrules/blob/master/README_MCP.md
Project-URL: Source, https://github.com/uengine/pyDMNrules
Project-URL: Tracker, https://github.com/uengine/pyDMNrules/issues
Keywords: dmn decision-model mcp model-context-protocol llm ai fastmcp claude
Classifier: Development Status :: 4 - Beta
Classifier: Intended Audience :: Developers
Classifier: Topic :: Software Development :: Libraries :: Python Modules
Classifier: Topic :: Scientific/Engineering :: Artificial Intelligence
Classifier: License :: OSI Approved :: MIT License
Classifier: Programming Language :: Python :: 3
Classifier: Programming Language :: Python :: 3.8
Classifier: Programming Language :: Python :: 3.9
Classifier: Programming Language :: Python :: 3.10
Classifier: Programming Language :: Python :: 3.11
Classifier: Programming Language :: Python :: 3.12
Classifier: Operating System :: OS Independent
Requires-Python: >=3.8
License-File: LICENSE
License-File: LICENSE_MCP
Requires-Dist: fastmcp>=0.4.0
Requires-Dist: pydantic>=2.0.0
Requires-Dist: aiofiles>=23.0.0
Requires-Dist: pydmnrules-enhanced>=1.6.0
Dynamic: author
Dynamic: author-email
Dynamic: classifier
Dynamic: description
Dynamic: description-content-type
Dynamic: home-page
Dynamic: keywords
Dynamic: license-file
Dynamic: project-url
Dynamic: requires-dist
Dynamic: requires-python
Dynamic: summary
